README.rst
ipandoc.py
setup.cfg
setup.py
iPandoc.egg-info/PKG-INFO
iPandoc.egg-info/SOURCES.txt
iPandoc.egg-info/dependency_links.txt
iPandoc.egg-info/top_level.txt