Metadata-Version: 1.1
Name: iPandoc
Version: 1.0.0
Summary: Pure Python bindings to the online Docverter Pandoc document format conversion API.
Home-page: http://github.com/karimbahgat/iPandoc
Author: Karim Bahgat
Author-email: karim.bahgat.norway@gmail.com
License: MIT
Keywords: pandoc document format conversion rst markdown docverter API
Platform: UNKNOWN
Classifier: License :: OSI Approved
Classifier: Programming Language :: Python
Classifier: Development Status :: 4 - Beta
Classifier: Intended Audience :: Developers
Classifier: Intended Audience :: Science/Research
Classifier: Intended Audience :: End Users/Desktop
